{
    "colorCodeStudio": "64647105",
    "colorCodeBricklink": "64647105",
    "colorCodeLDraw": "64647105",
    "colorCodeLDD": "64647105",
    "colorNameStudio": "Fine Trans-Orange",
    "colorNameBricklink": "FTorange",
    "colorNameLDraw": "FTorange",
    "colorNameLDD": "FTorange",
    "colorRGB": "#EF8E1B",
    "colorAlpha": "0.5",
    "categoryName": "Transparent Colors",
    "groupIndex": "5",
    "note": "o",
    "insRGB": "",
    "insCMYK": "",
    "categoryNickname": "Fine Transparent Colors"
}