{
    "colorCodeStudio": "64647208",
    "colorCodeBricklink": "64647208",
    "colorCodeLDraw": "64647208",
    "colorCodeLDD": "64647208",
    "colorNameStudio": "Semitrans-Yellow",
    "colorNameBricklink": "STyellow",
    "colorNameLDraw": "STyellow",
    "colorNameLDD": "STyellow",
    "colorRGB": "#F4CC2E",
    "colorAlpha": "0.5",
    "categoryName": "Transparent Colors",
    "groupIndex": "8",
    "note": "o",
    "insRGB": "",
    "insCMYK": "",
    "categoryNickname": "Semitransparent Colors"
}