{
    "colorCodeStudio": "64642106",
    "colorCodeBricklink": "64642106",
    "colorCodeLDraw": "64642106",
    "colorCodeLDD": "64642106",
    "colorNameStudio": "Smooth Reddish Gold",
    "colorNameBricklink": "Sreddishgold",
    "colorNameLDraw": "Sreddishgold",
    "colorNameLDD": "Sreddishgold",
    "colorRGB": "#c58a3e",
    "colorAlpha": "0.9",
    "categoryName": "Pearl Colors",
    "groupIndex": "7",
    "note": "o",
    "insRGB": "",
    "insCMYK": "",
    "categoryNickname": "Metal-Smooth Colors"
}