{
    "colorCodeStudio": "64646103",
    "colorCodeBricklink": "64646103",
    "colorCodeLDraw": "64646103",
    "colorCodeLDD": "64646103",
    "colorNameStudio": "Fine Flat Silver Metallic",
    "colorNameBricklink": "Fflatsilvermetallic",
    "colorNameLDraw": "Fflatsilvermetallic",
    "colorNameLDD": "Fflatsilvermetallic",
    "colorRGB": "#8C8C8C",
    "colorAlpha": "1",
    "categoryName": "Pearl Colors",
    "groupIndex": "-1",
    "note": "o",
    "insRGB": "",
    "insCMYK": "",
    "categoryNickname": "Metal-Fine Colors"
}