{
    "colorCodeStudio": "64647412",
    "colorCodeBricklink": "64647412",
    "colorCodeLDraw": "64647412",
    "colorCodeLDD": "64647412",
    "colorNameStudio": "Fluorescent Trans-Green",
    "colorNameBricklink": "FTgreen",
    "colorNameLDraw": "FTgreen",
    "colorNameLDD": "FTgreen",
    "colorRGB": "#227740",
    "colorAlpha": "0.5",
    "categoryName": "Transparent Colors",
    "groupIndex": "12",
    "note": "o",
    "insRGB": "",
    "insCMYK": "",
    "categoryNickname": "Fluorescent Transparent Colors"
}