{
    "colorCodeStudio": "64641005",
    "colorCodeBricklink": "64641005",
    "colorCodeLDraw": "64641005",
    "colorCodeLDD": "64641005",
    "colorNameStudio": "Rau Orange",
    "colorNameBricklink": "Rorange",
    "colorNameLDraw": "Rorange",
    "colorNameLDD": "Rorange",
    "colorRGB": "#ff5f08",
    "colorAlpha": "0.8",
    "categoryName": "Transparent Colors",
    "groupIndex": "5",
    "note": "o",
    "insRGB": "",
    "insCMYK": "0,50,95,0",
    "categoryNickname": "Rau Transparent Colors"
}