{
    "colorCodeStudio": "64649503",
    "colorCodeBricklink": "64649503",
    "colorCodeLDraw": "64649503",
    "colorCodeLDD": "64649503",
    "colorNameStudio": "Marbled Orange-Black - Carapar",
    "colorNameBricklink": "Carapar",
    "colorNameLDraw": "Carapar",
    "colorNameLDD": "Carapar",
    "colorRGB": "#D79A1C",
    "colorAlpha": "1",
    "categoryName": "Transparent Colors",
    "groupIndex": "1",
    "note": "o",
    "insRGB": "",
    "insCMYK": "",
    "categoryNickname": "Marbled Patterns"
}