{
    "colorCodeStudio": "64647318",
    "colorCodeBricklink": "64647318",
    "colorCodeLDraw": "64647318",
    "colorCodeLDD": "64647318",
    "colorNameStudio": "Soft Trans-Light Blue Violet",
    "colorNameBricklink": "STlightblueviolet",
    "colorNameLDraw": "STlightblueviolet",
    "colorNameLDD": "STlightblueviolet",
    "colorRGB": "#6BABE4",
    "colorAlpha": "0.5",
    "categoryName": "Transparent Colors",
    "groupIndex": "16",
    "note": "o",
    "insRGB": "",
    "insCMYK": "",
    "categoryNickname": "Soft Transparent Colors"
}