{
    "colorCodeStudio": "64648605",
    "colorCodeBricklink": "64648605",
    "colorCodeLDraw": "64648605",
    "colorCodeLDD": "64648605",
    "colorNameStudio": "Legacy Volume Glow Neon Green",
    "colorNameBricklink": "LVGNgreen",
    "colorNameLDraw": "LVGNgreen",
    "colorNameLDD": "LVGNgreen",
    "colorRGB": "#63b701",
    "colorAlpha": "0.7",
    "categoryName": "Transparent Colors",
    "groupIndex": "12",
    "note": "o",
    "insRGB": "",
    "insCMYK": "",
    "categoryNickname": "Legacy Volume Glow Neon Colors"
}