{
    "colorCodeStudio": "64643041",
    "colorCodeBricklink": "64643041",
    "colorCodeLDraw": "64643041",
    "colorCodeLDD": "64643041",
    "colorNameStudio": "Light Grey Poisoned Kanohi",
    "colorNameBricklink": "Light Gray Poisoned Kanohi",
    "colorNameLDraw": "lightgreyPK",
    "colorNameLDD": "lightgrayPK",
    "colorRGB": "#9AA09C",
    "colorAlpha": "1",
    "categoryName": "Pearl Colors",
    "groupIndex": "-1",
    "note": "o",
    "insRGB": "",
    "insCMYK": "",
    "categoryNickname": "Infected Colors"
}