{
    "colorCodeStudio": "64649011",
    "colorCodeBricklink": "64649011",
    "colorCodeLDraw": "64649011",
    "colorCodeLDD": "64649011",
    "colorNameStudio": "Light Bluish Grey with Silver Center",
    "colorNameBricklink": "Light Bluish Gray with Silver Center",
    "colorNameLDraw": "lightbluishgreyWSC",
    "colorNameLDD": "lightbluishgrayWSC",
    "colorRGB": "#9fa4a8",
    "colorAlpha": "1",
    "categoryName": "Pearl Colors",
    "groupIndex": "-1",
    "note": "o",
    "insRGB": "",
    "insCMYK": "",
    "categoryNickname": "Blended Center Patterns"
}