{
    "colorCodeStudio": "64649019",
    "colorCodeBricklink": "64649019",
    "colorCodeLDraw": "64649019",
    "colorCodeLDD": "64649019",
    "colorNameStudio": "Medium Blue with Silver Center",
    "colorNameBricklink": "mediumblueWSC",
    "colorNameLDraw": "mediumblueWSC",
    "colorNameLDD": "mediumblueWSC",
    "colorRGB": "#5b9cd0",
    "colorAlpha": "1",
    "categoryName": "Pearl Colors",
    "groupIndex": "16",
    "note": "o",
    "insRGB": "",
    "insCMYK": "",
    "categoryNickname": "Blended Center Patterns"
}