{
    "colorCodeStudio": "33002",
    "colorCodeBricklink": "33002",
    "colorCodeLDraw": "33002",
    "colorCodeLDD": "33002",
    "colorNameStudio": "Metallic Orange Glowing Silver",
    "colorNameBricklink": "Metallic Orange Glowing Silver",
    "colorNameLDraw": "Metallic Orange Glowing Silver",
    "colorNameLDD": "Metallic Orange Glowing Silver",
    "colorRGB": "#ff963c",
    "colorAlpha": "1.0",
    "categoryName": "Metallic Colors",
    "groupIndex": "5",
    "note": "to_lego",
    "insRGB": "",
    "insCMYK": "",
    "categoryNickname": "Metallic Glowing Colors"
}