{
    "colorCodeStudio": "64649224",
    "colorCodeBricklink": "64649224",
    "colorCodeLDraw": "64649224",
    "colorCodeLDD": "64649224",
    "colorNameStudio": "Dark Orange with Silver Top",
    "colorNameBricklink": "darkorangeWST",
    "colorNameLDraw": "darkorangeWST",
    "colorNameLDD": "darkorangeWST",
    "colorRGB": "#a85400",
    "colorAlpha": "1",
    "categoryName": "Pearl Colors",
    "groupIndex": "5",
    "note": "o",
    "insRGB": "",
    "insCMYK": "",
    "categoryNickname": "Blended Top Patterns"
}