{
    "colorCodeStudio": "64649242",
    "colorCodeBricklink": "64649242",
    "colorCodeLDraw": "64649242",
    "colorCodeLDD": "64649242",
    "colorNameStudio": "Dark Grey with Silver Top",
    "colorNameBricklink": "Dark Gray with Silver Top",
    "colorNameLDraw": "darkgreyWST",
    "colorNameLDD": "darkgrayWST",
    "colorRGB": "#6C6D5B",
    "colorAlpha": "1",
    "categoryName": "Pearl Colors",
    "groupIndex": "-1",
    "note": "o",
    "insRGB": "",
    "insCMYK": "",
    "categoryNickname": "Blended Top Patterns"
}